{
  "unevaluatedProperties" : false,
  "properties" : {
    "message" : {
      "title" : "message",
      "description" : "Messages for the agent",
      "lightning:type" : "lightning__textType",
      "lightning:isPII" : false,
      "copilotAction:isDisplayable" : true,
      "copilotAction:isUsedByPlanner" : true
    },
    "ptoIDs" : {
      "title" : "ptoIDs",
      "description" : "IDs for the PTO request",
      "maxItems" : 2000,
      "items" : {
        "lightning:type" : "lightning__textType"
      },
      "lightning:type" : "lightning__listType",
      "lightning:isPII" : false,
      "copilotAction:isDisplayable" : true,
      "copilotAction:isUsedByPlanner" : true
    },
    "success" : {
      "title" : "success",
      "description" : "Indicates if the request was successful or not",
      "lightning:type" : "lightning__booleanType",
      "lightning:isPII" : false,
      "copilotAction:isDisplayable" : true,
      "copilotAction:isUsedByPlanner" : true
    }
  },
  "lightning:type" : "lightning__objectType"
}